{
  "name": "Nora Fowler",
  "age": 43,
  "address": {
    "street": "Gojep Junction",
    "city": "Vunojnu",
    "state": "MA",
    "zip": "25406"
  },
  "contact": {
    "phone": "(873) 906-3201",
    "servicePhone": "800612692"
  },
  "birthday": "1975-03-30T22:38:28.728Z",
  "ip": "242.163.40.227",
  "foo": "bar",
  "profile": {
    "about": "Sogow hetud weezu ekusogug wom guvab ofte upronce sefjuzo ho ocko wirofze ajcimjef sac pahkuhvet avkumupo men. Petgi ekujuir haluw bozese naribesug tir cesosi umjod ife mil seditpe telzoz fu tu jacra suj fathim rok. Sej azotojguc ocozuk ud japsohibe re zokab rippo izufib onouk welsur sududle ju ke tevisteh. Udah sa nuhiw ucuv beicoivu newacogut tocefba lugoswu kiabaog huva ufi rate kiftinit kisli bumcomal leg.",
    "bio": "Gim nu edzakjuc bego vaci reh los lipar hogmab jadpiz buege waf cuopiwa tuamihe jibzetuj tepa. Dod nad ede na ela lusoima jeccur aztaazo sesbo jiwos ci jatmali jug warkakcek. Ca biv peiw ap cutcaz icomaj nud an foz pidi femgo tumuodi toj sicdutog. Ji bemfuhere rihow dag ene cehet ripfacer hiz jij zu hi bakaba heluso. Elutig wudfoko fuce nuthiz gi copzi buvravor ona cih ili timbigoj fedfilnik levjej efawuvla fo damimevo. Ku cubuzuk ge cowzu lisitop watijzuz kodci ki ahovibal ratuv jir ucfo so."
  },
  "apiKey": "df2c6764273b08748bd27983e1287208163e115cbb2a05182edd86cc123d9970",
  "currency": {
    "code": "BSD",
    "name": "Bahamas Dollar"
  }
}